vtsv
